experiment_collection_core/__init__.py
experiment_collection_core/service_pb2.py
experiment_collection_core/service_pb2_grpc.py
experiment_collection_server/__init__.py
experiment_collection_server/__main__.py
experiment_collection_server/service.py
experiment_collection_server/db/__init__.py
experiment_collection_server/db/storage_abc.py
experiment_collection_server/db/storage_postgresql.py
experiment_collection_server/db/storage_sqlite.py
experiment_collection_server-0.2.7.dist-info/LICENSE
experiment_collection_server-0.2.7.dist-info/METADATA
experiment_collection_server-0.2.7.dist-info/WHEEL
experiment_collection_server-0.2.7.dist-info/entry_points.txt
experiment_collection_server-0.2.7.dist-info/top_level.txt
experiment_collection_server-0.2.7.dist-info/RECORD
