Metadata-Version: 2.1
Name: experiment-collection-server
Version: 0.2.7
Summary: Experiment collection
Home-page: https://github.com/AsciiShell/experiment_collection
Author: AsciiShell (Aleksey Podchezertsev)
Author-email: dev@asciishell.ru
License: MIT
Keywords: python3
Platform: UNKNOWN
Classifier: Intended Audience :: Developers
Classifier: Programming Language :: Python :: 3
Classifier: Programming Language :: Python :: 3.6
Classifier: Programming Language :: Python :: 3.7
Classifier: Programming Language :: Python :: 3.8
Classifier: License :: OSI Approved :: MIT License
Classifier: Operating System :: POSIX
Classifier: Operating System :: POSIX :: Linux
Requires-Python: >=3.6
Requires-Dist: grpcio (~=1.34.0)
Requires-Dist: protobuf (~=3.14.0)
Requires-Dist: ConfigArgParse (~=1.2.3)
Requires-Dist: setproctitle (~=1.2.2)
Requires-Dist: psycopg2 (~=2.8.6)
